d2b_yaml.py
d2b_yaml-1.0.0.dist-info/entry_points.txt
d2b_yaml-1.0.0.dist-info/WHEEL
d2b_yaml-1.0.0.dist-info/METADATA
d2b_yaml-1.0.0.dist-info/RECORD
